README.md
setup.py
groestlcoin_hash2/__init__.py
groestlcoin_hash2/groestl.py
groestlcoin_hash2.egg-info/PKG-INFO
groestlcoin_hash2.egg-info/SOURCES.txt
groestlcoin_hash2.egg-info/dependency_links.txt
groestlcoin_hash2.egg-info/top_level.txt