Metadata-Version: 1.0
Name: groestlcoin-hash2
Version: 1.0
Summary: Pure python Groestlcoin hash algorithm.
Home-page: https://github.com/groestlcoin/groestlcoin-hash-pure-python
Author: Kefkius
Author-email: kefkius@mail.com
License: UNKNOWN
Keywords: groestlcoin,grs
Platform: UNKNOWN
